Metadata-Version: 2.1
Name: waifuim.py
Version: 2.4.5
Summary: A Python wrapper for waifu.im API.
Home-page: https://github.com/Waifu-im/waifuim.py
Author: Buco
Author-email: bucolo33fr@gmail.com
License: MIT
Project-URL: Issue tracker, https://github.com/Waifu-im/waifuim.py/issues
Platform: UNKNOWN
Classifier: Development Status :: 5 - Production/Stable
Classifier: License :: OSI Approved :: MIT License
Classifier: Intended Audience :: Developers
Classifier: Natural Language :: English
Classifier: Operating System :: OS Independent
Classifier: Programming Language :: Python :: 3
Classifier: Programming Language :: Python :: 3.6
Classifier: Programming Language :: Python :: 3.7
Classifier: Programming Language :: Python :: 3.8
Classifier: Programming Language :: Python :: 3.9
Classifier: Topic :: Internet
Classifier: Topic :: Software Development :: Libraries
Classifier: Topic :: Software Development :: Libraries :: Python Modules
Classifier: Topic :: Utilities
Requires-Python: >=3.6
License-File: LICENSE
